green_invoice/__init__.py
green_invoice/client.py
green_invoice/exceptions.py
green_invoice/models.py
green_invoice/resources.py
green_invoice/version.py
green_invoice-1.3.0.dist-info/licenses/LICENSE
green_invoice-1.3.0.dist-info/METADATA
green_invoice-1.3.0.dist-info/WHEEL
green_invoice-1.3.0.dist-info/top_level.txt
green_invoice-1.3.0.dist-info/RECORD
