Metadata-Version: 2.4
Name: green_invoice
Version: 1.3.0
Summary: A Python 3 module to interact with the Green Invoice API.
Home-page: https://github.com/yanivps/green-invoice
Author: Yaniv Pinchas
License: LICENSE
Classifier: Development Status :: 3 - Alpha
Classifier: Intended Audience :: Developers
Classifier: License :: OSI Approved :: MIT License
Classifier: Programming Language :: Python :: 3
Classifier: Programming Language :: Python :: 3.8
Classifier: Programming Language :: Python :: 3.9
Classifier: Programming Language :: Python :: 3.10
Classifier: Programming Language :: Python :: 3.11
Classifier: Programming Language :: Python :: 3.12
Classifier: Programming Language :: Python :: 3.13
License-File: LICENSE
Requires-Dist: certifi>=2024.0.0
Requires-Dist: chardet>=5.0.0
Requires-Dist: idna>=3.0
Requires-Dist: lxml>=6.0.0
Requires-Dist: requests>=2.32.0
Requires-Dist: urllib3>=2.0.0
Dynamic: author
Dynamic: classifier
Dynamic: description
Dynamic: description-content-type
Dynamic: home-page
Dynamic: license
Dynamic: license-file
Dynamic: requires-dist
Dynamic: summary
